aiotools/__init__.py
aiotools/cancel.py
aiotools/compat.py
aiotools/context.py
aiotools/defer.py
aiotools/fork.py
aiotools/func.py
aiotools/iter.py
aiotools/py.typed
aiotools/server.py
aiotools/supervisor.py
aiotools/taskcontext.py
aiotools/taskscope.py
aiotools/timeouts.py
aiotools/timer.py
aiotools/types.py
aiotools/utils.py
aiotools/taskgroup/__init__.py
aiotools/taskgroup/base.py
aiotools/taskgroup/common.py
aiotools/taskgroup/persistent.py
aiotools/taskgroup/types.py
aiotools-2.2.3.dist-info/licenses/LICENSE
aiotools-2.2.3.dist-info/METADATA
aiotools-2.2.3.dist-info/WHEEL
aiotools-2.2.3.dist-info/top_level.txt
aiotools-2.2.3.dist-info/RECORD
